hfmonthlyreport/__init__.py
hfmonthlyreport-0.8.dist-info/METADATA
hfmonthlyreport-0.8.dist-info/WHEEL
hfmonthlyreport-0.8.dist-info/top_level.txt
hfmonthlyreport-0.8.dist-info/RECORD
