Metadata-Version: 2.1
Name: hfmonthlyreport
Version: 0.8
Summary: Send monthly file count only to monthly report server
Author: VishalJain_NIOT
Author-email: allwhc07@gmail.com
Requires-Dist: requests
Requires-Dist: pyperclip==1.8.2
Requires-Dist: qrcode
